LICENSE
MANIFEST.in
README.md
requirements.txt
setup.py
cert_core/__init__.py
cert_core/cert_model/__init__.py
cert_core/cert_model/model.py
cert_core/cert_store/__init__.py
cert_core/cert_store/certificate_store.py
cert_core/cert_store/config.py
cert_core/cert_store/gridfs_key_value_store.py
cert_core/cert_store/helpers.py
cert_core_bloxberg.egg-info/PKG-INFO
cert_core_bloxberg.egg-info/SOURCES.txt
cert_core_bloxberg.egg-info/dependency_links.txt
cert_core_bloxberg.egg-info/requires.txt
cert_core_bloxberg.egg-info/top_level.txt
tests/__init__.py
tests/test_certificate_store.py
tests/test_init.py
tests/test_model.py