Metadata-Version: 1.0
Name: cert-core-bloxberg
Version: 2.1.2
Summary: Blockcerts-bloxberg core models for python
Home-page: https://github.com/crossoveranx/cert-core.git
Author: info@bloxberg.org
Author-email: info@bloxberg.org
License: MIT
Platform: UNKNOWN
